<com.nucleus.makerchecker.GridConfiguration>
	<entityClass>com.nucleus.cas.loan.LoanApplicationVo</entityClass>
	<jspName>masterDatatable</jspName>
	<recordUrl>/app/LoanApplication/edit/</recordUrl>
	<entityNameMRKey>LoanApplicationVo</entityNameMRKey>
	<masterEntityConfiguration>
		<autoApproval>false</autoApproval>
		<entityUpdateInfoList>
		</entityUpdateInfoList>
	</masterEntityConfiguration>
	<springBeanName>casLoanApplicationService</springBeanName>
	<key>LoanApplicationVo</key>
	<initializingPath></initializingPath>
	<columnConfigurationList>
		<com.nucleus.makerchecker.ColumnConfiguration>
			<titleKey>key.id</titleKey>
			<width>125</width>
			<sortable>false</sortable>
			<hidden>false</hidden>
			<dataField>loanApplication.id</dataField>
			<columnType>string</columnType>
		</com.nucleus.makerchecker.ColumnConfiguration>
		<com.nucleus.makerchecker.ColumnConfiguration>
			<titleKey>key.uuid</titleKey>
			<width>125</width>
			<sortable>false</sortable>
			<hidden>true</hidden>
			<dataField>loanApplication.uuid</dataField>
			<columnType>string</columnType>
		</com.nucleus.makerchecker.ColumnConfiguration>
		<com.nucleus.makerchecker.ColumnConfiguration>
			<titleKey>key.customerId</titleKey>
			<width>125</width>
			<sortable>true</sortable>
			<hidden>false</hidden>
			<dataField>customer.id</dataField>
			<columnType>link</columnType>
		</com.nucleus.makerchecker.ColumnConfiguration>
		<com.nucleus.makerchecker.ColumnConfiguration>
			<titleKey>key.customerName</titleKey>
			<width>125</width>
			<sortable>true</sortable>
			<hidden>false</hidden>
			<dataField>fullName</dataField>
			<columnType>string</columnType>
		</com.nucleus.makerchecker.ColumnConfiguration>
		<com.nucleus.makerchecker.ColumnConfiguration>
			<titleKey>key.sourceDate</titleKey>
			<width>125</width>
			<sortable>true</sortable>
			<hidden>false</hidden>
			<dataField>applicationDetails.applicationCreationDate</dataField>
			<columnType>string</columnType>
		</com.nucleus.makerchecker.ColumnConfiguration>
		<com.nucleus.makerchecker.ColumnConfiguration>
			<titleKey>key.sourceChannel</titleKey>
			<width>125</width>
			<sortable>true</sortable>
			<hidden>false</hidden>
			<dataField>applicationDetails.applicationSource</dataField>
			<columnType>string</columnType>
		</com.nucleus.makerchecker.ColumnConfiguration>
		<com.nucleus.makerchecker.ColumnConfiguration>
			<titleKey>key.phoneNumber</titleKey>
			<width>125</width>
			<sortable>true</sortable>
			<hidden>false</hidden>
			<dataField>contactInfo.phoneNumbers.phoneNumber</dataField>
			<columnType>string</columnType>
		</com.nucleus.makerchecker.ColumnConfiguration>
		<com.nucleus.makerchecker.ColumnConfiguration>
			<titleKey>key.actions</titleKey>
			<width>125</width>
			<sortable>false</sortable>
			<hidden>false</hidden>
			<dataField>actions</dataField>
			<columnType>string</columnType>
		</com.nucleus.makerchecker.ColumnConfiguration>
	</columnConfigurationList>
	<actionConfigurationList>
		<com.nucleus.makerchecker.ActionConfiguration>
			<action>Edit</action>
			<imagePath>/images/Edit.png</imagePath>
			<actionUrl>/app/LoanApplicationVo/edit/</actionUrl>
			<text>false</text>
		</com.nucleus.makerchecker.ActionConfiguration>
		<com.nucleus.makerchecker.ActionConfiguration>
			<action>Delete</action>
			<imagePath>/images/Delete.png</imagePath>
			<actionUrl>/app/master/LoanApplicationVo/LoanApplicationVo/delete</actionUrl>
			<text>false</text>
		</com.nucleus.makerchecker.ActionConfiguration>
	</actionConfigurationList>
</com.nucleus.makerchecker.GridConfiguration>